Metadata-Version: 2.1
Name: mocktail
Version: 0.0.2
Summary: Non-alcoholic Mockito-style when-then utilities for unittest.mock
Home-page: https://github.com/koirikivi/mocktail.git
Author: Rainer Koirikivi
Author-email: rainer@koirikivi.fi
License: UNKNOWN
Keywords: testing,mock,unittest,mockito,when
Platform: UNKNOWN
Classifier: Development Status :: 3 - Alpha
Classifier: Intended Audience :: Developers
Classifier: Topic :: Software Development :: Testing
Classifier: Topic :: Software Development :: Testing :: Mocking
Classifier: License :: OSI Approved :: MIT License
Classifier: Programming Language :: Python :: 3
Classifier: Programming Language :: Python :: 3.6
Classifier: Programming Language :: Python :: 3.7
Classifier: Programming Language :: Python :: 3.8
Provides-Extra: testing
